{
  "brand": "baba",
  "assortmentCode": "BH0048",
  "feedUrl": "https://www.baba.hu/home.productfeed.json",
  "totalUrlsChecked": 62,
  "problematicPagesFound": 15,
  "successfulPages": 47,
  "errors": 0,
  "duration": "0.09s",
  "speed": "688.89 URLs/s",
  "problematicPages": [
    {
      "type": "problematic",
      "brand": "baba",
      "assortmentCode": "BH0048",
      "feedUrl": "https://www.baba.hu/home.productfeed.json",
      "url": "https://www.baba.hu/p/baba-ferfi-tusfurdo-erzekeny-borre-3in1-400-ml.html/08720181637964",
      "gtin": "08720181637964",
      "checkedAt": "2026-03-15T08:52:03.342Z",
      "debug": {
        "url": "https://bin.cartwire.co/services/hashlanginfobutton?brand_name=baba&locale=hu-hu&brand_code=BH0048&gtin=08720181637964",
        "scriptPreview": "<script type=\"text/javascript\" class=\"cwscript_kana\">\n  setTimeout(function () {\n    console.log(\"There is a problem with one of the products Buy It Now (BIN) button on this Product Page. BIN button i"
      }
    },
    {
      "type": "problematic",
      "brand": "baba",
      "assortmentCode": "BH0048",
      "feedUrl": "https://www.baba.hu/home.productfeed.json",
      "url": "https://www.baba.hu/p/baba-frissito-tusfurdo-bogyosgyumolcs-illat-750-ml.html/08720181637971",
      "gtin": "08720181637971",
      "checkedAt": "2026-03-15T08:52:03.335Z",
      "debug": {
        "url": "https://bin.cartwire.co/services/hashlanginfobutton?brand_name=baba&locale=hu-hu&brand_code=BH0048&gtin=08720181637971",
        "scriptPreview": "<script type=\"text/javascript\" class=\"cwscript_kana\">\n  setTimeout(function () {\n    console.log(\"There is a problem with one of the products Buy It Now (BIN) button on this Product Page. BIN button i"
      }
    },
    {
      "type": "problematic",
      "brand": "baba",
      "assortmentCode": "BH0048",
      "feedUrl": "https://www.baba.hu/home.productfeed.json",
      "url": "https://www.baba.hu/p/baba-folyekony-szappan-utantolto-antibakterialis-eukaliptusz-500-ml.html/08720181740343",
      "gtin": "08720181740343",
      "checkedAt": "2026-03-15T08:52:03.345Z",
      "debug": {
        "url": "https://bin.cartwire.co/services/hashlanginfobutton?brand_name=baba&locale=hu-hu&brand_code=BH0048&gtin=08720181740343",
        "scriptPreview": "<script type=\"text/javascript\" class=\"cwscript_kana\">\n  setTimeout(function () {\n    console.log(\"There is a problem with one of the products Buy It Now (BIN) button on this Product Page. BIN button i"
      }
    },
    {
      "type": "problematic",
      "brand": "baba",
      "assortmentCode": "BH0048",
      "feedUrl": "https://www.baba.hu/home.productfeed.json",
      "url": "https://www.baba.hu/p/baba-folyekony-szappan-antibakterialis-eukaliptusz-250-ml.html/08720181740367",
      "gtin": "08720181740367",
      "checkedAt": "2026-03-15T08:52:03.341Z",
      "debug": {
        "url": "https://bin.cartwire.co/services/hashlanginfobutton?brand_name=baba&locale=hu-hu&brand_code=BH0048&gtin=08720181740367",
        "scriptPreview": "<script type=\"text/javascript\" class=\"cwscript_kana\">\n  setTimeout(function () {\n    console.log(\"There is a problem with one of the products Buy It Now (BIN) button on this Product Page. BIN button i"
      }
    },
    {
      "type": "problematic",
      "brand": "baba",
      "assortmentCode": "BH0048",
      "feedUrl": "https://www.baba.hu/home.productfeed.json",
      "url": "https://www.baba.hu/p/baba-folyekony-szappan-utantolto-antibakterialis-eukaliptusz-750-ml.html/08720181741067",
      "gtin": "08720181741067",
      "checkedAt": "2026-03-15T08:52:03.345Z",
      "debug": {
        "url": "https://bin.cartwire.co/services/hashlanginfobutton?brand_name=baba&locale=hu-hu&brand_code=BH0048&gtin=08720181741067",
        "scriptPreview": "<script type=\"text/javascript\" class=\"cwscript_kana\">\n  setTimeout(function () {\n    console.log(\"There is a problem with one of the products Buy It Now (BIN) button on this Product Page. BIN button i"
      }
    },
    {
      "type": "problematic",
      "brand": "baba",
      "assortmentCode": "BH0048",
      "feedUrl": "https://www.baba.hu/home.productfeed.json",
      "url": "https://www.baba.hu/p/baba-konnymentes-gyereksampon-400-ml.html/08710447462744",
      "gtin": "08710447462744",
      "checkedAt": "2026-03-15T08:52:03.332Z",
      "debug": {
        "url": "https://bin.cartwire.co/services/hashlanginfobutton?brand_name=baba&locale=hu-hu&brand_code=BH0048&gtin=08710447462744",
        "scriptPreview": "<script type=\"text/javascript\" class=\"cwscript_kana\">\n  setTimeout(function () {\n    console.log(\"There is a problem with one of the products Buy It Now (BIN) button on this Product Page. BIN button i"
      }
    },
    {
      "type": "problematic",
      "brand": "baba",
      "assortmentCode": "BH0048",
      "feedUrl": "https://www.baba.hu/home.productfeed.json",
      "url": "https://www.baba.hu/p/baba-frissito-tusfurdo-cseresznye-illat-400-ml.html/08710908324079",
      "gtin": "08710908324079",
      "checkedAt": "2026-03-15T08:52:03.342Z",
      "debug": {
        "url": "https://bin.cartwire.co/services/hashlanginfobutton?brand_name=baba&locale=hu-hu&brand_code=BH0048&gtin=08710908324079",
        "scriptPreview": "<script type=\"text/javascript\" class=\"cwscript_kana\">\n  setTimeout(function () {\n    console.log(\"There is a problem with one of the products Buy It Now (BIN) button on this Product Page. BIN button i"
      }
    },
    {
      "type": "problematic",
      "brand": "baba",
      "assortmentCode": "BH0048",
      "feedUrl": "https://www.baba.hu/home.productfeed.json",
      "url": "https://www.baba.hu/p/baba-aloe-veras-frissito-testapolo-400-ml.html/08712561672511",
      "gtin": "08712561672511",
      "checkedAt": "2026-03-15T08:52:03.330Z",
      "debug": {
        "url": "https://bin.cartwire.co/services/hashlanginfobutton?brand_name=baba&locale=hu-hu&brand_code=BH0048&gtin=08712561672511",
        "scriptPreview": "<script type=\"text/javascript\" class=\"cwscript_kana\">\n  setTimeout(function () {\n    console.log(\"There is a problem with one of the products Buy It Now (BIN) button on this Product Page. BIN button i"
      }
    },
    {
      "type": "problematic",
      "brand": "baba",
      "assortmentCode": "BH0048",
      "feedUrl": "https://www.baba.hu/home.productfeed.json",
      "url": "https://www.baba.hu/p/baba-kakaovajas-kenyeztet-testapolo-400-ml.html/08712561672535",
      "gtin": "08712561672535",
      "checkedAt": "2026-03-15T08:52:03.359Z",
      "debug": {
        "url": "https://bin.cartwire.co/services/hashlanginfobutton?brand_name=baba&locale=hu-hu&brand_code=BH0048&gtin=08712561672535",
        "scriptPreview": "<script type=\"text/javascript\" class=\"cwscript_kana\">\n  setTimeout(function () {\n    console.log(\"There is a problem with one of the products Buy It Now (BIN) button on this Product Page. BIN button i"
      }
    },
    {
      "type": "problematic",
      "brand": "baba",
      "assortmentCode": "BH0048",
      "feedUrl": "https://www.baba.hu/home.productfeed.json",
      "url": "https://www.baba.hu/p/baba-melyhidratalo-testapolo-400ml.html/08712561684521",
      "gtin": "08712561684521",
      "checkedAt": "2026-03-15T08:52:03.330Z",
      "debug": {
        "url": "https://bin.cartwire.co/services/hashlanginfobutton?brand_name=baba&locale=hu-hu&brand_code=BH0048&gtin=08712561684521",
        "scriptPreview": "<script type=\"text/javascript\" class=\"cwscript_kana\">\n  setTimeout(function () {\n    console.log(\"There is a problem with one of the products Buy It Now (BIN) button on this Product Page. BIN button i"
      }
    },
    {
      "type": "problematic",
      "brand": "baba",
      "assortmentCode": "BH0048",
      "feedUrl": "https://www.baba.hu/home.productfeed.json",
      "url": "https://www.baba.hu/p/baba-kamillas-nyugtato-testapolo-400-ml.html/08712561704489",
      "gtin": "08712561704489",
      "checkedAt": "2026-03-15T08:52:03.340Z",
      "debug": {
        "url": "https://bin.cartwire.co/services/hashlanginfobutton?brand_name=baba&locale=hu-hu&brand_code=BH0048&gtin=08712561704489",
        "scriptPreview": "<script type=\"text/javascript\" class=\"cwscript_kana\">\n  setTimeout(function () {\n    console.log(\"There is a problem with one of the products Buy It Now (BIN) button on this Product Page. BIN button i"
      }
    },
    {
      "type": "problematic",
      "brand": "baba",
      "assortmentCode": "BH0048",
      "feedUrl": "https://www.baba.hu/home.productfeed.json",
      "url": "https://www.baba.hu/p/baba-intenziv-testapolo-400ml.html/08712561704502",
      "gtin": "08712561704502",
      "checkedAt": "2026-03-15T08:52:03.335Z",
      "debug": {
        "url": "https://bin.cartwire.co/services/hashlanginfobutton?brand_name=baba&locale=hu-hu&brand_code=BH0048&gtin=08712561704502",
        "scriptPreview": "<script type=\"text/javascript\" class=\"cwscript_kana\">\n  setTimeout(function () {\n    console.log(\"There is a problem with one of the products Buy It Now (BIN) button on this Product Page. BIN button i"
      }
    },
    {
      "type": "problematic",
      "brand": "baba",
      "assortmentCode": "BH0048",
      "feedUrl": "https://www.baba.hu/home.productfeed.json",
      "url": "https://www.baba.hu/p/baba-frissito-tusfurdo-gorogdinnye-illat-400-ml.html/08717163761182",
      "gtin": "08717163761182",
      "checkedAt": "2026-03-15T08:52:03.336Z",
      "debug": {
        "url": "https://bin.cartwire.co/services/hashlanginfobutton?brand_name=baba&locale=hu-hu&brand_code=BH0048&gtin=08717163761182",
        "scriptPreview": "<script type=\"text/javascript\" class=\"cwscript_kana\">\n  setTimeout(function () {\n    console.log(\"There is a problem with one of the products Buy It Now (BIN) button on this Product Page. BIN button i"
      }
    },
    {
      "type": "problematic",
      "brand": "baba",
      "assortmentCode": "BH0048",
      "feedUrl": "https://www.baba.hu/home.productfeed.json",
      "url": "https://www.baba.hu/p/baba-kremtusfurdo-antibakterialis-osszetevovel-gyomber-400-ml.html/08720181074059",
      "gtin": "08720181074059",
      "checkedAt": "2026-03-15T08:52:03.338Z",
      "debug": {
        "url": "https://bin.cartwire.co/services/hashlanginfobutton?brand_name=baba&locale=hu-hu&brand_code=BH0048&gtin=08720181074059",
        "scriptPreview": "<script type=\"text/javascript\" class=\"cwscript_kana\">\n  setTimeout(function () {\n    console.log(\"There is a problem with one of the products Buy It Now (BIN) button on this Product Page. BIN button i"
      }
    },
    {
      "type": "problematic",
      "brand": "baba",
      "assortmentCode": "BH0048",
      "feedUrl": "https://www.baba.hu/home.productfeed.json",
      "url": "https://www.baba.hu/p/baba-kenyezteto-tusfurdo-edesmandula-illat-400-ml.html/08720181338182",
      "gtin": "08720181338182",
      "checkedAt": "2026-03-15T08:52:03.332Z",
      "debug": {
        "url": "https://bin.cartwire.co/services/hashlanginfobutton?brand_name=baba&locale=hu-hu&brand_code=BH0048&gtin=08720181338182",
        "scriptPreview": "<script type=\"text/javascript\" class=\"cwscript_kana\">\n  setTimeout(function () {\n    console.log(\"There is a problem with one of the products Buy It Now (BIN) button on this Product Page. BIN button i"
      }
    }
  ],
  "errorPages": []
}