{
  "generatedAt": "2026-03-12T12:28:41.684Z",
  "brand": "walls",
  "assortmentCode": "BF0765",
  "feedUrl": "https://www.selectaphilippines.com/home.productfeed.json",
  "totalUrlsChecked": 92,
  "problematicPagesFound": 0,
  "successfulPages": [
    {
      "type": "successful",
      "url": "https://www.selectaphilippines.com/p/supreme-cookies-&-cream-ice-cream.html/04800086035929",
      "gtin": "04800086035929",
      "checkedAt": "2026-03-12T12:28:26.892Z"
    },
    {
      "type": "successful",
      "url": "https://www.selectaphilippines.com/p/2-in-1-double-dutch-and-rocky-road.html/04800086038647",
      "gtin": "04800086038647",
      "checkedAt": "2026-03-12T12:28:26.889Z"
    },
    {
      "type": "successful",
      "url": "https://www.selectaphilippines.com/p/2-in-1-rocky-road-cookies-&-cream.html/04800086040633",
      "gtin": "04800086040633",
      "checkedAt": "2026-03-12T12:28:26.765Z"
    },
    {
      "type": "successful",
      "url": "https://www.selectaphilippines.com/p/supreme-cookies-&-cream-ice-cream-solo-pack.html/04800086043627",
      "gtin": "04800086043627",
      "checkedAt": "2026-03-12T12:28:27.512Z"
    },
    {
      "type": "successful",
      "url": "https://www.selectaphilippines.com/p/cornetto-white-rose.html/08851932469555",
      "gtin": "08851932469555",
      "checkedAt": "2026-03-12T12:28:27.464Z"
    },
    {
      "type": "successful",
      "url": "https://www.selectaphilippines.com/p/hersheys-cookies-n-chocolate-ice-cream-solo-pack.html/04800086045133",
      "gtin": "04800086045133",
      "checkedAt": "2026-03-12T12:28:27.523Z"
    },
    {
      "type": "successful",
      "url": "https://www.selectaphilippines.com/p/watermelon-slice-ice-cream-stick.html/04800086045973",
      "gtin": "04800086045973",
      "checkedAt": "2026-03-12T12:28:27.586Z"
    },
    {
      "type": "successful",
      "url": "https://www.selectaphilippines.com/p/2-in-1-rocky-road-cookies-&-cream.html/04800086049742",
      "gtin": "04800086049742",
      "checkedAt": "2026-03-12T12:28:27.449Z"
    },
    {
      "type": "successful",
      "url": "https://www.selectaphilippines.com/p/magnum-minis-almond.html/08999999035631",
      "gtin": "08999999035631",
      "checkedAt": "2026-03-12T12:28:34.497Z"
    }
  ],
  "errors": 83,
  "duration": "17.73s",
  "speedMetrics": "5.19 URLs/second",
  "problematicPages": [],
  "errorPages": [
    {
      "type": "error",
      "url": "https://www.selectaphilippines.com/p/supreme-coffee-crumble-ice-cream.html/04800086035943",
      "error": "request to https://www.selectaphilippines.com/p/supreme-coffee-crumble-ice-cream.html/04800086035943 failed, reason: Socket timeout",
      "checkedAt": "2026-03-12T12:28:33.622Z"
    },
    {
      "type": "error",
      "url": "https://www.selectaphilippines.com/p/supreme-double-dutch-ice-cream-3l.html/04800086035950",
      "error": "HTTP Error: 429 Too Many Requests",
      "checkedAt": "2026-03-12T12:28:25.900Z"
    },
    {
      "type": "error",
      "url": "https://www.selectaphilippines.com/p/super-thick-mango.html/04800086036001",
      "error": "HTTP Error: 429 Too Many Requests",
      "checkedAt": "2026-03-12T12:28:26.043Z"
    },
    {
      "type": "error",
      "url": "https://www.selectaphilippines.com/p/super-thick-super-chocolate-ice-cream.html/04800086036018",
      "error": "request to https://www.selectaphilippines.com/p/super-thick-super-chocolate-ice-cream.html/04800086036018 failed, reason: Socket timeout",
      "checkedAt": "2026-03-12T12:28:33.621Z"
    },
    {
      "type": "error",
      "url": "https://www.selectaphilippines.com/p/super-thick-vanilla-ice-cream-3l.html/04800086036032",
      "error": "request to https://www.selectaphilippines.com/p/super-thick-vanilla-ice-cream-3l.html/04800086036032 failed, reason: Socket timeout",
      "checkedAt": "2026-03-12T12:28:33.621Z"
    },
    {
      "type": "error",
      "url": "https://www.selectaphilippines.com/p/super-thick-vanilla-ice-cream.html/04800086036049",
      "error": "HTTP Error: 429 Too Many Requests",
      "checkedAt": "2026-03-12T12:28:25.668Z"
    },
    {
      "type": "error",
      "url": "https://www.selectaphilippines.com/p/super-thick-ube-royale-ice-cream.html/04800086036063",
      "error": "HTTP Error: 429 Too Many Requests",
      "checkedAt": "2026-03-12T12:28:26.303Z"
    },
    {
      "type": "error",
      "url": "https://www.selectaphilippines.com/p/super-thick-strawberry-ice-cream.html/04800086036094",
      "error": "HTTP Error: 429 Too Many Requests",
      "checkedAt": "2026-03-12T12:28:25.912Z"
    },
    {
      "type": "error",
      "url": "https://www.selectaphilippines.com/p/supreme-quezo-real-ice-cream.html/04800086036162",
      "error": "request to https://www.selectaphilippines.com/p/supreme-quezo-real-ice-cream.html/04800086036162 failed, reason: Socket timeout",
      "checkedAt": "2026-03-12T12:28:33.620Z"
    },
    {
      "type": "error",
      "url": "https://www.selectaphilippines.com/p/supreme-rocky-road-ice-cream.html/04800086036186",
      "error": "request to https://www.selectaphilippines.com/p/supreme-rocky-road-ice-cream.html/04800086036186 failed, reason: Socket timeout",
      "checkedAt": "2026-03-12T12:28:33.622Z"
    },
    {
      "type": "error",
      "url": "https://www.selectaphilippines.com/p/cookies-&-cream-ice-cream-stick.html/04800086036513",
      "error": "HTTP Error: 429 Too Many Requests",
      "checkedAt": "2026-03-12T12:28:25.637Z"
    },
    {
      "type": "error",
      "url": "https://www.selectaphilippines.com/p/2-in-1-double-dutch-rocky-road.html/04800086038630",
      "error": "HTTP Error: 429 Too Many Requests",
      "checkedAt": "2026-03-12T12:28:25.788Z"
    },
    {
      "type": "error",
      "url": "https://www.selectaphilippines.com/p/2-in-1-quezo-real-buco-salad.html/04800086038708",
      "error": "request to https://www.selectaphilippines.com/p/2-in-1-quezo-real-buco-salad.html/04800086038708 failed, reason: Socket timeout",
      "checkedAt": "2026-03-12T12:28:32.700Z"
    },
    {
      "type": "error",
      "url": "https://www.selectaphilippines.com/p/2-in-1-rocky-road-cookies-&-cream-750ml.html/04800086040657",
      "error": "HTTP Error: 429 Too Many Requests",
      "checkedAt": "2026-03-12T12:28:25.749Z"
    },
    {
      "type": "error",
      "url": "https://www.selectaphilippines.com/p/2-in-1-double-dutch-cookies-&-cream.html/04800086040671",
      "error": "request to https://www.selectaphilippines.com/p/2-in-1-double-dutch-cookies-&-cream.html/04800086040671 failed, reason: Socket timeout",
      "checkedAt": "2026-03-12T12:28:32.700Z"
    },
    {
      "type": "error",
      "url": "https://www.selectaphilippines.com/p/2-in-1-double-dutch-cookies-&-cream-750ml.html/04800086040688",
      "error": "HTTP Error: 429 Too Many Requests",
      "checkedAt": "2026-03-12T12:28:25.809Z"
    },
    {
      "type": "error",
      "url": "https://www.selectaphilippines.com/p/supreme-double-dutch-ice-cream-750ml.html/04800086040879",
      "error": "HTTP Error: 429 Too Many Requests",
      "checkedAt": "2026-03-12T12:28:25.719Z"
    },
    {
      "type": "error",
      "url": "https://www.selectaphilippines.com/p/supreme-rocky-road-ice-cream-750ml.html/04800086040886",
      "error": "HTTP Error: 429 Too Many Requests",
      "checkedAt": "2026-03-12T12:28:26.026Z"
    },
    {
      "type": "error",
      "url": "https://www.selectaphilippines.com/p/supreme-cookies-&-cream-ice-cream.html/04800086040893",
      "error": "HTTP Error: 404 Not Found",
      "checkedAt": "2026-03-12T12:28:33.451Z"
    },
    {
      "type": "error",
      "url": "https://www.selectaphilippines.com/p/supreme-coffee-crumble-ice-cream-750ml.html/04800086040909",
      "error": "HTTP Error: 429 Too Many Requests",
      "checkedAt": "2026-03-12T12:28:25.767Z"
    },
    {
      "type": "error",
      "url": "https://www.selectaphilippines.com/p/supreme-quezo-real-ice-cream-750ml.html/04800086040916",
      "error": "HTTP Error: 429 Too Many Requests",
      "checkedAt": "2026-03-12T12:28:25.711Z"
    },
    {
      "type": "error",
      "url": "https://www.selectaphilippines.com/p/mango-graham-cake.html/04800086042293",
      "error": "HTTP Error: 429 Too Many Requests",
      "checkedAt": "2026-03-12T12:28:26.067Z"
    },
    {
      "type": "error",
      "url": "https://www.selectaphilippines.com/p/supreme-mango-graham-cake-ice-cream.html/04800086042309",
      "error": "request to https://www.selectaphilippines.com/p/supreme-mango-graham-cake-ice-cream.html/04800086042309 failed, reason: Socket timeout",
      "checkedAt": "2026-03-12T12:28:33.620Z"
    },
    {
      "type": "error",
      "url": "https://www.selectaphilippines.com/p/supreme-black-forest-ice-cream.html/04800086043368",
      "error": "request to https://www.selectaphilippines.com/p/supreme-black-forest-ice-cream.html/04800086043368 failed, reason: Socket timeout",
      "checkedAt": "2026-03-12T12:28:33.621Z"
    },
    {
      "type": "error",
      "url": "https://www.selectaphilippines.com/p/hersheys-milk-chocolate-with-almonds-ice-cream.html/04800086043467",
      "error": "HTTP Error: 429 Too Many Requests",
      "checkedAt": "2026-03-12T12:28:25.784Z"
    },
    {
      "type": "error",
      "url": "https://www.selectaphilippines.com/p/double-dutch-solo-pack.html/04800086043603",
      "error": "HTTP Error: 429 Too Many Requests",
      "checkedAt": "2026-03-12T12:28:25.656Z"
    },
    {
      "type": "error",
      "url": "https://www.selectaphilippines.com/p/supreme-rocky-road-ice-cream-solo-pack.html/04800086043610",
      "error": "HTTP Error: 429 Too Many Requests",
      "checkedAt": "2026-03-12T12:28:25.911Z"
    },
    {
      "type": "error",
      "url": "https://www.selectaphilippines.com/p/supreme-coffee-crumble-ice-cream-solo-pack.html/04800086043634",
      "error": "request to https://www.selectaphilippines.com/p/supreme-coffee-crumble-ice-cream-solo-pack.html/04800086043634 failed, reason: Socket timeout",
      "checkedAt": "2026-03-12T12:28:33.621Z"
    },
    {
      "type": "error",
      "url": "https://www.selectaphilippines.com/p/supreme-pistachios-&-cashews-ice-cream-solo-pack.html/04800086043641",
      "error": "HTTP Error: 429 Too Many Requests",
      "checkedAt": "2026-03-12T12:28:25.679Z"
    },
    {
      "type": "error",
      "url": "https://www.selectaphilippines.com/p/hersheys-milk-chocolate-with-almonds-ice-cream-solo-pack.html/04800086043672",
      "error": "HTTP Error: 429 Too Many Requests",
      "checkedAt": "2026-03-12T12:28:25.692Z"
    },
    {
      "type": "error",
      "url": "https://www.selectaphilippines.com/p/cornetto-ube-caramel.html/04800086050519",
      "error": "HTTP Error: 429 Too Many Requests",
      "checkedAt": "2026-03-12T12:28:25.780Z"
    },
    {
      "type": "error",
      "url": "https://www.selectaphilippines.com/p/quezo-real-ice-cream-stick.html/04800086036506",
      "error": "request to https://www.selectaphilippines.com/p/quezo-real-ice-cream-stick.html/04800086036506 failed, reason: Socket timeout",
      "checkedAt": "2026-03-12T12:28:33.608Z"
    },
    {
      "type": "error",
      "url": "https://www.selectaphilippines.com/p/rocky-road-ice-cream-stick.html/04800086036520",
      "error": "request to https://www.selectaphilippines.com/p/rocky-road-ice-cream-stick.html/04800086036520 failed, reason: Socket timeout",
      "checkedAt": "2026-03-12T12:28:33.621Z"
    },
    {
      "type": "error",
      "url": "https://www.selectaphilippines.com/p/creamdae-3in1-choco-keso-ube.html/04800086040527",
      "error": "HTTP Error: 429 Too Many Requests",
      "checkedAt": "2026-03-12T12:28:25.662Z"
    },
    {
      "type": "error",
      "url": "https://www.selectaphilippines.com/p/creamdae-ube-hapi-pack.html/04800086044365",
      "error": "HTTP Error: 429 Too Many Requests",
      "checkedAt": "2026-03-12T12:28:25.663Z"
    },
    {
      "type": "error",
      "url": "https://www.selectaphilippines.com/p/creamdae-choco-hapi-pack.html/04800086044372",
      "error": "request to https://www.selectaphilippines.com/p/creamdae-choco-hapi-pack.html/04800086044372 failed, reason: Socket timeout",
      "checkedAt": "2026-03-12T12:28:33.621Z"
    },
    {
      "type": "error",
      "url": "https://www.selectaphilippines.com/p/creamdae-keso-hapi-pack.html/04800086044389",
      "error": "HTTP Error: 429 Too Many Requests",
      "checkedAt": "2026-03-12T12:28:26.277Z"
    },
    {
      "type": "error",
      "url": "https://www.selectaphilippines.com/p/hersheys-cookies-n-creme-ice-cream-solo-pack.html/04800086045126",
      "error": "HTTP Error: 429 Too Many Requests",
      "checkedAt": "2026-03-12T12:28:25.766Z"
    },
    {
      "type": "error",
      "url": "https://www.selectaphilippines.com/p/supreme-pistachios-&-cashews-ice-cream.html/04800086045560",
      "error": "request to https://www.selectaphilippines.com/p/supreme-pistachios-&-cashews-ice-cream.html/04800086045560 failed, reason: Socket timeout",
      "checkedAt": "2026-03-12T12:28:33.620Z"
    },
    {
      "type": "error",
      "url": "https://www.selectaphilippines.com/p/boom-boom-pinipig-chocolate-ice-cream-stick.html/04800086045768",
      "error": "request to https://www.selectaphilippines.com/p/boom-boom-pinipig-chocolate-ice-cream-stick.html/04800086045768 failed, reason: Socket timeout",
      "checkedAt": "2026-03-12T12:28:32.700Z"
    },
    {
      "type": "error",
      "url": "https://www.selectaphilippines.com/p/mango-slush-ice-cream-stick.html/04800086046031",
      "error": "HTTP Error: 429 Too Many Requests",
      "checkedAt": "2026-03-12T12:28:29.433Z"
    },
    {
      "type": "error",
      "url": "https://www.selectaphilippines.com/p/cornetto-disc-black-choco-cookie.html/04800086046482",
      "error": "HTTP Error: 429 Too Many Requests",
      "checkedAt": "2026-03-12T12:28:25.678Z"
    },
    {
      "type": "error",
      "url": "https://www.selectaphilippines.com/p/creamdae-ube-cup.html/04800086046970",
      "error": "HTTP Error: 429 Too Many Requests",
      "checkedAt": "2026-03-12T12:28:24.872Z"
    },
    {
      "type": "error",
      "url": "https://www.selectaphilippines.com/p/creamdae-choco-cup.html/04800086046987",
      "error": "HTTP Error: 429 Too Many Requests",
      "checkedAt": "2026-03-12T12:28:26.292Z"
    },
    {
      "type": "error",
      "url": "https://www.selectaphilippines.com/p/supreme-coco-mango-mochi-ice-cream.html/04800086047151",
      "error": "request to https://www.selectaphilippines.com/p/supreme-coco-mango-mochi-ice-cream.html/04800086047151 failed, reason: Socket timeout",
      "checkedAt": "2026-03-12T12:28:33.620Z"
    },
    {
      "type": "error",
      "url": "https://www.selectaphilippines.com/p/selecta-boom-boom-cookies-&-cream-ice-cream-stick.html/04800086047472",
      "error": "request to https://www.selectaphilippines.com/p/selecta-boom-boom-cookies-&-cream-ice-cream-stick.html/04800086047472 failed, reason: Socket timeout",
      "checkedAt": "2026-03-12T12:28:33.622Z"
    },
    {
      "type": "error",
      "url": "https://www.selectaphilippines.com/p/supreme-choco-almond-fudge-ice-cream.html/04800086047625",
      "error": "request to https://www.selectaphilippines.com/p/supreme-choco-almond-fudge-ice-cream.html/04800086047625 failed, reason: Socket timeout",
      "checkedAt": "2026-03-12T12:28:33.622Z"
    },
    {
      "type": "error",
      "url": "https://www.selectaphilippines.com/p/creamdae-3in1-1-choco-keso-ube-mango.html/04800086047717",
      "error": "HTTP Error: 429 Too Many Requests",
      "checkedAt": "2026-03-12T12:28:29.437Z"
    },
    {
      "type": "error",
      "url": "https://www.selectaphilippines.com/p/supreme-ube-macapuno-ice-cream.html/04800086048721",
      "error": "HTTP Error: 429 Too Many Requests",
      "checkedAt": "2026-03-12T12:28:25.911Z"
    },
    {
      "type": "error",
      "url": "https://www.selectaphilippines.com/p/supreme-halo-halo-ice-cream.html/04800086048745",
      "error": "request to https://www.selectaphilippines.com/p/supreme-halo-halo-ice-cream.html/04800086048745 failed, reason: Socket timeout",
      "checkedAt": "2026-03-12T12:28:33.621Z"
    },
    {
      "type": "error",
      "url": "https://www.selectaphilippines.com/p/cornetto-disc-matcha-crumble.html/04800086049551",
      "error": "request to https://www.selectaphilippines.com/p/cornetto-disc-matcha-crumble.html/04800086049551 failed, reason: Socket timeout",
      "checkedAt": "2026-03-12T12:28:33.622Z"
    },
    {
      "type": "error",
      "url": "https://www.selectaphilippines.com/p/creamdae-3in1-choco-mango-ube-750-ml.html/04800086049681",
      "error": "request to https://www.selectaphilippines.com/p/creamdae-3in1-choco-mango-ube-750-ml.html/04800086049681 failed, reason: Socket timeout",
      "checkedAt": "2026-03-12T12:28:33.622Z"
    },
    {
      "type": "error",
      "url": "https://www.selectaphilippines.com/p/selecta-chocky.html/04800086049797",
      "error": "request to https://www.selectaphilippines.com/p/selecta-chocky.html/04800086049797 failed, reason: Socket timeout",
      "checkedAt": "2026-03-12T12:28:33.622Z"
    },
    {
      "type": "error",
      "url": "https://www.selectaphilippines.com/p/2-in-1-mango-float-ube-cake.html/04800086050045",
      "error": "HTTP Error: 429 Too Many Requests",
      "checkedAt": "2026-03-12T12:28:25.921Z"
    },
    {
      "type": "error",
      "url": "https://www.selectaphilippines.com/p/selecta-sundae-choco-cup.html/04800086050120",
      "error": "HTTP Error: 429 Too Many Requests",
      "checkedAt": "2026-03-12T12:28:26.043Z"
    },
    {
      "type": "error",
      "url": "https://www.selectaphilippines.com/p/selecta-crunchy-max.html/04800086050168",
      "error": "HTTP Error: 429 Too Many Requests",
      "checkedAt": "2026-03-12T12:28:25.910Z"
    },
    {
      "type": "error",
      "url": "https://www.selectaphilippines.com/p/selecta-coco-ube.html/04800086050236",
      "error": "request to https://www.selectaphilippines.com/p/selecta-coco-ube.html/04800086050236 failed, reason: Socket timeout",
      "checkedAt": "2026-03-12T12:28:33.620Z"
    },
    {
      "type": "error",
      "url": "https://www.selectaphilippines.com/p/selecta-coco-melon.html/04800086050250",
      "error": "HTTP Error: 429 Too Many Requests",
      "checkedAt": "2026-03-12T12:28:25.745Z"
    },
    {
      "type": "error",
      "url": "https://www.selectaphilippines.com/p/cornetto-berry-crazy-for-yoh.html/04800086050298",
      "error": "HTTP Error: 429 Too Many Requests",
      "checkedAt": "2026-03-12T12:28:25.987Z"
    },
    {
      "type": "error",
      "url": "https://www.selectaphilippines.com/p/creamdae-3in1-choco-vanilla-strawberry-750-ml.html/04800086050304",
      "error": "request to https://www.selectaphilippines.com/p/creamdae-3in1-choco-vanilla-strawberry-750-ml.html/04800086050304 failed, reason: Socket timeout",
      "checkedAt": "2026-03-12T12:28:33.620Z"
    },
    {
      "type": "error",
      "url": "https://www.selectaphilippines.com/p/creamdae-3in1-1-choco-vanilla-strawberry-ube.html/04800086050311",
      "error": "request to https://www.selectaphilippines.com/p/creamdae-3in1-1-choco-vanilla-strawberry-ube.html/04800086050311 failed, reason: Socket timeout",
      "checkedAt": "2026-03-12T12:28:33.620Z"
    },
    {
      "type": "error",
      "url": "https://www.selectaphilippines.com/p/creamdae-3in1-ube-mango-avocado-750-ml.html/04800086050328",
      "error": "request to https://www.selectaphilippines.com/p/creamdae-3in1-ube-mango-avocado-750-ml.html/04800086050328 failed, reason: Socket timeout",
      "checkedAt": "2026-03-12T12:28:33.620Z"
    },
    {
      "type": "error",
      "url": "https://www.selectaphilippines.com/p/selecta-ice-pop-berry-choco.html/04800086050588",
      "error": "HTTP Error: 429 Too Many Requests",
      "checkedAt": "2026-03-12T12:28:25.911Z"
    },
    {
      "type": "error",
      "url": "https://www.selectaphilippines.com/p/selecta-ice-pop-milky-coffee.html/04800086050595",
      "error": "request to https://www.selectaphilippines.com/p/selecta-ice-pop-milky-coffee.html/04800086050595 failed, reason: Socket timeout",
      "checkedAt": "2026-03-12T12:28:33.621Z"
    },
    {
      "type": "error",
      "url": "https://www.selectaphilippines.com/p/magnum-ice-cream-pint-white.html/08714100290408",
      "error": "request to https://www.selectaphilippines.com/p/magnum-ice-cream-pint-white.html/08714100290408 failed, reason: Socket timeout",
      "checkedAt": "2026-03-12T12:28:33.622Z"
    },
    {
      "type": "error",
      "url": "https://www.selectaphilippines.com/p/selecta-tornado-grape.html/08851932310352",
      "error": "HTTP Error: 429 Too Many Requests",
      "checkedAt": "2026-03-12T12:28:25.900Z"
    },
    {
      "type": "error",
      "url": "https://www.selectaphilippines.com/p/selecta-dragon-pop.html/08851932346016",
      "error": "HTTP Error: 429 Too Many Requests",
      "checkedAt": "2026-03-12T12:28:25.721Z"
    },
    {
      "type": "error",
      "url": "https://www.selectaphilippines.com/p/selecta-bites-time!.html/08851932441438",
      "error": "HTTP Error: 429 Too Many Requests",
      "checkedAt": "2026-03-12T12:28:25.912Z"
    },
    {
      "type": "error",
      "url": "https://www.selectaphilippines.com/p/calippo-red-strawberry.html/08851932460125",
      "error": "request to https://www.selectaphilippines.com/p/calippo-red-strawberry.html/08851932460125 failed, reason: Socket timeout",
      "checkedAt": "2026-03-12T12:28:33.621Z"
    },
    {
      "type": "error",
      "url": "https://www.selectaphilippines.com/p/calippo-blue-lemon.html/08851932460132",
      "error": "request to https://www.selectaphilippines.com/p/calippo-blue-lemon.html/08851932460132 failed, reason: Socket timeout",
      "checkedAt": "2026-03-12T12:28:33.621Z"
    },
    {
      "type": "error",
      "url": "https://www.selectaphilippines.com/p/selecta-winnie-the-pooh-honey-milk-&-strawberry-ice-cream.html/08851932473897",
      "error": "request to https://www.selectaphilippines.com/p/selecta-winnie-the-pooh-honey-milk-&-strawberry-ice-cream.html/08851932473897 failed, reason: Socket timeout",
      "checkedAt": "2026-03-12T12:28:33.622Z"
    },
    {
      "type": "error",
      "url": "https://www.selectaphilippines.com/p/magnum-almond-bar.html/08999999005610",
      "error": "request to https://www.selectaphilippines.com/p/magnum-almond-bar.html/08999999005610 failed, reason: Socket timeout",
      "checkedAt": "2026-03-12T12:28:33.622Z"
    },
    {
      "type": "error",
      "url": "https://www.selectaphilippines.com/p/magnum-classic-bar.html/08999999005689",
      "error": "request to https://www.selectaphilippines.com/p/magnum-classic-bar.html/08999999005689 failed, reason: Socket timeout",
      "checkedAt": "2026-03-12T12:28:41.670Z"
    },
    {
      "type": "error",
      "url": "https://www.selectaphilippines.com/p/magnum-minis-ice-cream-stick-almond-6x45ml.html/08999999035624",
      "error": "HTTP Error: 429 Too Many Requests",
      "checkedAt": "2026-03-12T12:28:34.294Z"
    },
    {
      "type": "error",
      "url": "https://www.selectaphilippines.com/p/magnum-ice-cream-stick-white-almond.html/08999999045555",
      "error": "request to https://www.selectaphilippines.com/p/magnum-ice-cream-stick-white-almond.html/08999999045555 failed, reason: Socket timeout",
      "checkedAt": "2026-03-12T12:28:41.683Z"
    },
    {
      "type": "error",
      "url": "https://www.selectaphilippines.com/p/magnum-minis-cookies-and-cream-&-almond-&-classic.html/08999999569235",
      "error": "request to https://www.selectaphilippines.com/p/magnum-minis-cookies-and-cream-&-almond-&-classic.html/08999999569235 failed, reason: Socket timeout",
      "checkedAt": "2026-03-12T12:28:41.682Z"
    },
    {
      "type": "error",
      "url": "https://www.selectaphilippines.com/p/magnum-choco-luxe-bar.html/08999999595586",
      "error": "request to https://www.selectaphilippines.com/p/magnum-choco-luxe-bar.html/08999999595586 failed, reason: Socket timeout",
      "checkedAt": "2026-03-12T12:28:41.682Z"
    },
    {
      "type": "error",
      "url": "https://www.selectaphilippines.com/p/magnum-mango-yoghurt-parfait.html/08999999600822",
      "error": "HTTP Error: 404 Not Found",
      "checkedAt": "2026-03-12T12:28:39.995Z"
    },
    {
      "type": "error",
      "url": "https://www.selectaphilippines.com/p/magnum-minis-mango-yogurt-&-almond-&-classic.html/08999999603502",
      "error": "HTTP Error: 404 Not Found",
      "checkedAt": "2026-03-12T12:28:40.036Z"
    },
    {
      "type": "error",
      "url": "https://www.selectaphilippines.com/p/cornetto-chocolate-ice-cream.html/14800086040265",
      "error": "request to https://www.selectaphilippines.com/p/cornetto-chocolate-ice-cream.html/14800086040265 failed, reason: Socket timeout",
      "checkedAt": "2026-03-12T12:28:41.682Z"
    },
    {
      "type": "error",
      "url": "https://www.selectaphilippines.com/p/cornetto-vanilla-ice-cream.html/14800086040272",
      "error": "request to https://www.selectaphilippines.com/p/cornetto-vanilla-ice-cream.html/14800086040272 failed, reason: Socket timeout",
      "checkedAt": "2026-03-12T12:28:41.683Z"
    },
    {
      "type": "error",
      "url": "https://www.selectaphilippines.com/p/cornetto-cookies-&-dream-ice-cream.html/14800086043303",
      "error": "request to https://www.selectaphilippines.com/p/cornetto-cookies-&-dream-ice-cream.html/14800086043303 failed, reason: Socket timeout",
      "checkedAt": "2026-03-12T12:28:41.682Z"
    },
    {
      "type": "error",
      "url": "https://www.selectaphilippines.com/p/cornetto-disc-white-choco-cookies-&-cream-ice-cream.html/14800086045673",
      "error": "HTTP Error: 404 Not Found",
      "checkedAt": "2026-03-12T12:28:39.822Z"
    }
  ]
}