{
  "brand": "baba",
  "assortmentCode": "BH0048",
  "feedUrl": "https://www.baba.hu/home.productfeed.json",
  "totalUrlsChecked": 62,
  "problematicPagesFound": 5,
  "successfulPages": 57,
  "errors": 0,
  "duration": "0.78s",
  "speed": "79.49 URLs/s",
  "problematicPages": [
    {
      "type": "problematic",
      "brand": "baba",
      "assortmentCode": "BH0048",
      "feedUrl": "https://www.baba.hu/home.productfeed.json",
      "url": "https://www.baba.hu/p/baba-ferfi-tusfurdo-erzekeny-borre-3in1-400-ml.html/08720181637964",
      "gtin": "08720181637964",
      "checkedAt": "2026-03-13T09:36:20.394Z",
      "debug": {
        "url": "https://bin.cartwire.co/services/hashlanginfobutton?brand_name=baba&locale=hu-hu&brand_code=BH0048&gtin=08720181637964",
        "scriptPreview": "<script type=\"text/javascript\" class=\"cwscript_kana\">\n  setTimeout(function () {\n    console.log(\"There is a problem with one of the products Buy It Now (BIN) button on this Product Page. BIN button i"
      }
    },
    {
      "type": "problematic",
      "brand": "baba",
      "assortmentCode": "BH0048",
      "feedUrl": "https://www.baba.hu/home.productfeed.json",
      "url": "https://www.baba.hu/p/baba-frissito-tusfurdo-bogyosgyumolcs-illat-750-ml.html/08720181637971",
      "gtin": "08720181637971",
      "checkedAt": "2026-03-13T09:36:20.393Z",
      "debug": {
        "url": "https://bin.cartwire.co/services/hashlanginfobutton?brand_name=baba&locale=hu-hu&brand_code=BH0048&gtin=08720181637971",
        "scriptPreview": "<script type=\"text/javascript\" class=\"cwscript_kana\">\n  setTimeout(function () {\n    console.log(\"There is a problem with one of the products Buy It Now (BIN) button on this Product Page. BIN button i"
      }
    },
    {
      "type": "problematic",
      "brand": "baba",
      "assortmentCode": "BH0048",
      "feedUrl": "https://www.baba.hu/home.productfeed.json",
      "url": "https://www.baba.hu/p/baba-folyekony-szappan-utantolto-antibakterialis-eukaliptusz-500-ml.html/08720181740343",
      "gtin": "08720181740343",
      "checkedAt": "2026-03-13T09:36:20.468Z",
      "debug": {
        "url": "https://bin.cartwire.co/services/hashlanginfobutton?brand_name=baba&locale=hu-hu&brand_code=BH0048&gtin=08720181740343",
        "scriptPreview": "<script type=\"text/javascript\" class=\"cwscript_kana\">\n  setTimeout(function () {\n    console.log(\"There is a problem with one of the products Buy It Now (BIN) button on this Product Page. BIN button i"
      }
    },
    {
      "type": "problematic",
      "brand": "baba",
      "assortmentCode": "BH0048",
      "feedUrl": "https://www.baba.hu/home.productfeed.json",
      "url": "https://www.baba.hu/p/baba-folyekony-szappan-antibakterialis-eukaliptusz-250-ml.html/08720181740367",
      "gtin": "08720181740367",
      "checkedAt": "2026-03-13T09:36:20.458Z",
      "debug": {
        "url": "https://bin.cartwire.co/services/hashlanginfobutton?brand_name=baba&locale=hu-hu&brand_code=BH0048&gtin=08720181740367",
        "scriptPreview": "<script type=\"text/javascript\" class=\"cwscript_kana\">\n  setTimeout(function () {\n    console.log(\"There is a problem with one of the products Buy It Now (BIN) button on this Product Page. BIN button i"
      }
    },
    {
      "type": "problematic",
      "brand": "baba",
      "assortmentCode": "BH0048",
      "feedUrl": "https://www.baba.hu/home.productfeed.json",
      "url": "https://www.baba.hu/p/baba-folyekony-szappan-utantolto-antibakterialis-eukaliptusz-750-ml.html/08720181741067",
      "gtin": "08720181741067",
      "checkedAt": "2026-03-13T09:36:20.379Z",
      "debug": {
        "url": "https://bin.cartwire.co/services/hashlanginfobutton?brand_name=baba&locale=hu-hu&brand_code=BH0048&gtin=08720181741067",
        "scriptPreview": "<script type=\"text/javascript\" class=\"cwscript_kana\">\n  setTimeout(function () {\n    console.log(\"There is a problem with one of the products Buy It Now (BIN) button on this Product Page. BIN button i"
      }
    }
  ]
}